CHANGES.txt
CONTRIBUTORS.txt
MANIFEST.in
MIT-LICENSE.txt
README.md
setup.py
.git/COMMIT_EDITMSG
.git/HEAD
.git/config
.git/description
.git/index
.git/hooks/applypatch-msg.sample
.git/hooks/commit-msg.sample
.git/hooks/post-update.sample
.git/hooks/pre-applypatch.sample
.git/hooks/pre-commit.sample
.git/hooks/pre-push.sample
.git/hooks/pre-rebase.sample
.git/hooks/prepare-commit-msg.sample
.git/hooks/update.sample
.git/info/exclude
.git/logs/HEAD
.git/logs/refs/heads/master
.git/logs/refs/remotes/origin/master
.git/objects/20/5da6e045eba469b6b764010313e2d8224163ed
.git/objects/2b/40bdb3e9b8b487613c9e19d98a9d5f4a5c1c04
.git/objects/32/a913f9dd19adebd01b63bfd686ba7f2b26cc4b
.git/objects/32/f3972c5883c4dacdaad2a714dd76bac010180a
.git/objects/41/406a30e5f0be5329d4bc6a3a77747d3851f0fc
.git/objects/45/47c8d301e0b42b04b920efd704a7bef58b5e3a
.git/objects/46/4ac11b12f4e4836b238b3083ea9ea906db21f6
.git/objects/49/0da642b678fb45a60730d289d646c5f3c60bed
.git/objects/4f/12d5ec1fb65985060fa0f13fcea727b4e44dfc
.git/objects/50/bfbbf408bb1ca9a0c0e45da8f34eb136d65688
.git/objects/59/003d56e3fe71492a0a3f8ba089c8dae9498b39
.git/objects/63/28637c89b845cfb8d320c0bf4180c85d90cd1b
.git/objects/79/e997e5571c20747bca723cb2cf7083d3a98997
.git/objects/81/b10f03cb45f34e446f2749a7bece210c79ecb4
.git/objects/9a/f4ffccc6c442af216c78f6761f8d7b6dcc4bd7
.git/objects/b1/a563d56d32c13177326b86c4278c92f269943a
.git/objects/de/deedf68b0d03d6c52429b82eea8c04783efee9
.git/objects/e6/9de29bb2d1d6434b8b29ae775ad8c2e48c5391
.git/objects/f0/41609396afa83f1026bf9125cb1413f79f65fc
.git/objects/f6/9e06c0bc4508fffe322a61c2ac0d3c69cfb648
.git/objects/fc/4c5e09624a71fbe26ac45bbd6b302eb60834c3
.git/objects/fc/80254b619d488138a43632b617124a3d324702
.git/refs/heads/master
.git/refs/remotes/origin/master
dist/django-socketio-events-0.1.1.tar.gz
dist/django-socketio-events-0.1.2.tar.gz
dist/nodjango-0.1.0-py2.7.egg
dist/nodjango-0.1.0.tar.gz
django_socketio_events.egg-info/PKG-INFO
django_socketio_events.egg-info/SOURCES.txt
django_socketio_events.egg-info/dependency_links.txt
django_socketio_events.egg-info/pbr.json
django_socketio_events.egg-info/requires.txt
django_socketio_events.egg-info/top_level.txt
nodjango/__init__.py
nodjango/index.js
nodjango/package.json
nodjango.egg-info/PKG-INFO
nodjango.egg-info/SOURCES.txt
nodjango.egg-info/dependency_links.txt
nodjango.egg-info/requires.txt
nodjango.egg-info/top_level.txt
