Metadata-Version: 1.0
Name: django-socketio-events
Version: 0.1.2
Summary: Django package for socket.io via nodejs
Home-page: https://github.com/pztrick/django-socketio-events/
Author: Patrick Paul
Author-email: pztrick44@gmail.com
License: MIT-LICENSE.txt
Platform: UNKNOWN
